models/__init__.py
models/label.pkl
models/svc.pkl
models/vectorizer.pkl
visvmtagger/__init__.py
visvmtagger/tagger.py
visvmtagger/train.py
visvmtagger-1.0a0.dist-info/METADATA
visvmtagger-1.0a0.dist-info/RECORD
visvmtagger-1.0a0.dist-info/WHEEL
visvmtagger-1.0a0.dist-info/top_level.txt
vitagger/__init__.py
vitagger/tagger.py
vitagger/train.py
